tests/__init__.py
tests/test_hola.py
Mensajes_larg-5.0.dist-info/LICENSE
Mensajes_larg-5.0.dist-info/METADATA
Mensajes_larg-5.0.dist-info/WHEEL
Mensajes_larg-5.0.dist-info/top_level.txt
Mensajes_larg-5.0.dist-info/RECORD
