Metadata-Version: 2.1
Name: Mensajes-larg
Version: 5.0
Summary: Un paquete para saludar y despedir
Author: Luis A Ruiz
Author-email: luisarg59@gmail.com
Classifier: Environment :: Console
Classifier: Operating System :: OS Independent
Classifier: Programming Language :: Python
Classifier: Programming Language :: Python :: 3.11
Classifier: Topic :: Utilities
License-File: LICENSE
Requires-Dist: numpy (>=1.24.3)
